{"pageProps":{"recipe":{"raw":"---\ntitle: Old Bow River\ndescription: A Black Manhattan variation made with wheat whiskey and amaro vermouth.\nsummary: >\n    The Old Bow River is a twist on the Black Manhattan, featuring a local wheat whiskey from Wild Life Distillery in Canmore, Alberta. The sweet, earthy notes of the whiskey blend with the amaro vermouth, offering flavors of banana bread, cherries, and rich chocolate.\nauthor: Jordan Ranson\ntags: manhattan, amaro, vermouth, whiskey\ncreated: 2024-10-16\nmodified: 2024-10-16\nyield: 1\nyieldUnit: drink\ningredients:\n    Cocktail:\n        - qty: 2\n          unit: oz\n          name: Wild Life Wheat Whiskey\n          link: https://wildlifedistillery.ca/products/wild-life-distillery-wheat-whisky\n        - qty: 0.75\n          unit: oz\n          name: Cocci Dopo Teatro Vermouth Amaro\n          link: https://www.cocchi.it/en/wines/dopo-teatro-vermouth-amaro\n        - qty: 2\n          unit: dash\n          name: Xocolatl Mole Bitters\n        - qty: 1\n          unit: barspoon\n          name: Amarena Cherry Syrup\n    Garnish:\n        - qty: 1\n          unit: \n          name: Amerena Cherry\n\n---\n\n## Preparation\n\nAhead of time, chill a tumbler, coupe, or martini glass in the freezer.\n\n## Assembling the Drink\n\nFill a mixing glass with ice and add cocktail ingredients. Stir for 30 seconds then strain into your chilled glass. Garnish by dropping a cherry into the glass.\n","content":"<h2>Preparation</h2>\n<p>Ahead of time, chill a tumbler, coupe, or martini glass in the freezer.</p>\n<h2>Assembling the Drink</h2>\n<p>Fill a mixing glass with ice and add cocktail ingredients. Stir for 30 seconds then strain into your chilled glass. Garnish by dropping a cherry into the glass.</p>\n","attributes":{"title":"Old Bow River","description":"A Black Manhattan variation made with wheat whiskey and amaro vermouth.","summary":"<p>The Old Bow River is a twist on the Black Manhattan, featuring a local wheat whiskey from Wild Life Distillery in Canmore, Alberta. The sweet, earthy notes of the whiskey blend with the amaro vermouth, offering flavors of banana bread, cherries, and rich chocolate.</p>\n","author":"Jordan Ranson","tags":["manhattan","amaro","vermouth","whiskey"],"created":"2024-10-16T00:00:00.000Z","modified":"2024-10-16T00:00:00.000Z","yield":1,"yieldUnit":"drink","ingredients":{"Cocktail":[{"qty":2,"unit":"oz","name":"Wild Life Wheat Whiskey","link":"https://wildlifedistillery.ca/products/wild-life-distillery-wheat-whisky"},{"qty":0.75,"unit":"oz","name":"Cocci Dopo Teatro Vermouth Amaro","link":"https://www.cocchi.it/en/wines/dopo-teatro-vermouth-amaro"},{"qty":2,"unit":"dash","name":"Xocolatl Mole Bitters"},{"qty":1,"unit":"barspoon","name":"Amarena Cherry Syrup"}],"Garnish":[{"qty":1,"unit":null,"name":"Amerena Cherry"}]},"categoryId":"cocktails"}},"config":{"build":{"baseUrl":"https://www.recette.com/"},"template":{}},"searchContext":{"authors":[{"id":"jordan-ranson","name":"Jordan Ranson","recipes":[{"id":"old-bow-river","authorId":"jordan-ranson","categoryId":"cocktails"}]}],"recipes":[{"id":"old-bow-river","title":"Old Bow River","description":"A Black Manhattan variation made with wheat whiskey and amaro vermouth.","tags":["manhattan","amaro","vermouth","whiskey"],"categoryId":"cocktails","authorId":"jordan-ranson"}],"tags":[{"id":"manhattan","recipes":[{"id":"old-bow-river","authorId":"jordan-ranson","categoryId":"cocktails"}]},{"id":"amaro","recipes":[{"id":"old-bow-river","authorId":"jordan-ranson","categoryId":"cocktails"}]},{"id":"vermouth","recipes":[{"id":"old-bow-river","authorId":"jordan-ranson","categoryId":"cocktails"}]},{"id":"whiskey","recipes":[{"id":"old-bow-river","authorId":"jordan-ranson","categoryId":"cocktails"}]}],"taxonomies":[{"id":"cocktails","title":"Cocktails","recipes":[{"id":"old-bow-river","authorId":"jordan-ranson","categoryId":"cocktails"}]}]},"checksum":""},"__N_SSG":true}