{"raw":"---\ntitle: Old Bow River\ndescription: A Black Manhattan variation made with wheat whisky and amaro vermouth.\nsummary: >\n    The Old Bow River is a twist on the Black Manhattan, featuring a local wheat whisky from Wild Life Distillery in Canmore, Alberta. The sweet, earthy notes of the whisky blend with the amaro vermouth, offering flavors of banana bread, cherries, and rich chocolate.\nauthor: Jordan Ranson\ntags: manhattan, amaro, vermouth, whisky\ncreated: 2024-10-16\nmodified: 2024-10-16\nyield: 1\nyieldUnit: drink\ningredients:\n    Cocktail:\n        - qty: 2\n          unit: oz\n          name: Wild Life Wheat Whisky\n          link: https://wildlifedistillery.ca/products/wild-life-distillery-wheat-whisky\n        - qty: 0.75\n          unit: oz\n          name: Cocci Dopo Teatro Vermouth Amaro\n          link: https://www.cocchi.it/en/wines/dopo-teatro-vermouth-amaro\n        - qty: 2\n          unit: dash\n          name: Xocolatl Mole Bitters\n        - qty: 1\n          unit: barspoon\n          name: Amarena Cherry Syrup\n    Garnish:\n        - qty: 1\n          unit: \n          name: Amerena Cherry\n\n---\n\n## Preparation\n\nAhead of time, chill a tumbler, coupe, or martini glass in the freezer.\n\n## Assembling the Drink\n\nPlace a few ice cubes into a mixing glass and add cocktail ingredients. Stir for 30 seconds then strain into your chilled glass. Garnish by dropping a cherry into the glass.\n","content":"<h2>Preparation</h2>\n<p>Ahead of time, chill a tumbler, coupe, or martini glass in the freezer.</p>\n<h2>Assembling the Drink</h2>\n<p>Place a few ice cubes into a mixing glass and add cocktail ingredients. Stir for 30 seconds then strain into your chilled glass. Garnish by dropping a cherry into the glass.</p>\n","attributes":{"title":"Old Bow River","description":"A Black Manhattan variation made with wheat whisky and amaro vermouth.","summary":"<p>The Old Bow River is a twist on the Black Manhattan, featuring a local wheat whisky from Wild Life Distillery in Canmore, Alberta. The sweet, earthy notes of the whisky blend with the amaro vermouth, offering flavors of banana bread, cherries, and rich chocolate.</p>\n","author":"Jordan Ranson","tags":["manhattan","amaro","vermouth","whisky"],"created":"2024-10-16T00:00:00.000Z","modified":"2024-10-16T00:00:00.000Z","yield":1,"yieldUnit":"drink","ingredients":{"Cocktail":[{"qty":2,"unit":"oz","name":"Wild Life Wheat Whisky","link":"https://wildlifedistillery.ca/products/wild-life-distillery-wheat-whisky"},{"qty":0.75,"unit":"oz","name":"Cocci Dopo Teatro Vermouth Amaro","link":"https://www.cocchi.it/en/wines/dopo-teatro-vermouth-amaro"},{"qty":2,"unit":"dash","name":"Xocolatl Mole Bitters"},{"qty":1,"unit":"barspoon","name":"Amarena Cherry Syrup"}],"Garnish":[{"qty":1,"unit":null,"name":"Amerena Cherry"}]},"categoryId":"cocktails"}}