{"raw":"---\ntitle: Imperfect Manhattan\ndescription: A balanced twist on the classic Manhattan with equal parts rye whiskey and sweet vermouth.\nsummary: >\n    A twist on the classic Manhattan, this version strikes a balance with equal parts rye whiskey and sweet vermouth. Smooth and slightly less intense, it delivers a mellow sweetness with just the right amount of spice from the rye. Perfect for those who prefer a more approachable yet still bold cocktail.\nauthor: Jordan Ranson\ntags: manhattan, vermouth, rye, campari\ncreated: 2024-10-16\nmodified: 2024-10-16\nyield: 1\nyieldUnit: drink\ningredients:\n    Cocktail:\n        - qty: 1.5\n          unit: oz\n          name: Crown Royal Rye Whisky\n        - qty: 1.5\n          unit: oz\n          name: Noilly Prat Rouge Vermouth\n        - qty: 1\n          unit: barspoon\n          name: Campari\n    Garnish:\n        - qty: 1\n          unit: \n          name: Orange Twist\n\n---\n\n## Preparation\n\nPlace one large ice cube in a tumbler.\n\n## Assembling the Drink\n\nPlace a few ice cubes into a mixing glass and add cocktail ingredients. Stir for 30 seconds then strain into the tumbler. Express the orange twist over the glass then place on top of the ice cube.\n\n\n","content":"<h2>Preparation</h2>\n<p>Place one large ice cube in a tumbler.</p>\n<h2>Assembling the Drink</h2>\n<p>Place a few ice cubes into a mixing glass and add cocktail ingredients. Stir for 30 seconds then strain into the tumbler. Express the orange twist over the glass then place on top of the ice cube.</p>\n","attributes":{"title":"Imperfect Manhattan","description":"A balanced twist on the classic Manhattan with equal parts rye whiskey and sweet vermouth.","summary":"<p>A twist on the classic Manhattan, this version strikes a balance with equal parts rye whiskey and sweet vermouth. Smooth and slightly less intense, it delivers a mellow sweetness with just the right amount of spice from the rye. Perfect for those who prefer a more approachable yet still bold cocktail.</p>\n","author":"Jordan Ranson","tags":["manhattan","vermouth","rye","campari"],"created":"2024-10-16T00:00:00.000Z","modified":"2024-10-16T00:00:00.000Z","yield":1,"yieldUnit":"drink","ingredients":{"Cocktail":[{"qty":1.5,"unit":"oz","name":"Crown Royal Rye Whisky"},{"qty":1.5,"unit":"oz","name":"Noilly Prat Rouge Vermouth"},{"qty":1,"unit":"barspoon","name":"Campari"}],"Garnish":[{"qty":1,"unit":null,"name":"Orange Twist"}]},"categoryId":"cocktails"}}