{"raw":"---\ntitle: Wild Rose Sour\ndescription: A fruity and floral tequila sour made with reposado tequila, lime, strawberry, and rose.\nsummary: >\n    The Wild Rose Sour is a refreshing riff on a Tommy's Margarita, swapping out the agave syrup for a homemade strawberry rose syrup. This twist adds a subtle sweetness and floral note, perfectly balancing the tartness of the lime and enhancing the smooth, rich flavor of reposado tequila.\nauthor: Jordan Ranson\ntags: margarita, tequila, sour\ncreated: 2024-10-16\nmodified: 2024-10-16\nyield: 1\nyieldUnit: drink\ningredients:\n    Cocktail:\n        - qty: 2\n          unit: oz\n          name: Reposado Tequila\n        - qty: 0.75\n          unit: oz\n          name: Lime Juice\n        - qty: 0.75\n          unit: oz\n          name: Strawberry Rose Syrup\n        - qty: 1\n          unit: pinch\n          name: salt\n    Strawberry Rose Syrup:\n        - qty: 1\n          unit: cup\n          name: Water\n        - qty: 1\n          unit: cup\n          name: Frozen Strawberries\n        - qty: 1\n          unit: tbsp\n          name: Dried Rose Buds\n        - qty: 1\n          unit: cup\n          name: Agave Syrup\n    Garnish:\n        - qty: 1\n          unit: \n          name: Lime Wheel\n\n---\n\n## Preparation\n\nFill a tumbler with ice.\n\n## Assembling the Drink\n\nPut a scoop of ice into a cocktail shaker and add cocktail ingredients. Shake vigorously for 20 seconds. Strain into the tumbler. Garnish with a lime wheel.\n\n## Strawberry Rose Syrup\n\nIn a pot, bring water to a boil and add strawberries and rose buds. Cover and let simmer for 15 minutes.  Remove from heat and strain and discard the strawberries and rose buds from the water. \n\nAdd the water back to the pot on low heat and add the agave syrup. Gently stir until fully disolved then remove from heat and let cool. \n\nStore in an air-tight container and keep refrigerated.\n","content":"<h2>Preparation</h2>\n<p>Fill a tumbler with ice.</p>\n<h2>Assembling the Drink</h2>\n<p>Put a scoop of ice into a cocktail shaker and add cocktail ingredients. Shake vigorously for 20 seconds. Strain into the tumbler. Garnish with a lime wheel.</p>\n<h2>Strawberry Rose Syrup</h2>\n<p>In a pot, bring water to a boil and add strawberries and rose buds. Cover and let simmer for 15 minutes.  Remove from heat and strain and discard the strawberries and rose buds from the water. </p>\n<p>Add the water back to the pot on low heat and add the agave syrup. Gently stir until fully disolved then remove from heat and let cool. </p>\n<p>Store in an air-tight container and keep refrigerated.</p>\n","attributes":{"title":"Wild Rose Sour","description":"A fruity and floral tequila sour made with reposado tequila, lime, strawberry, and rose.","summary":"<p>The Wild Rose Sour is a refreshing riff on a Tommy&#39;s Margarita, swapping out the agave syrup for a homemade strawberry rose syrup. This twist adds a subtle sweetness and floral note, perfectly balancing the tartness of the lime and enhancing the smooth, rich flavor of reposado tequila.</p>\n","author":"Jordan Ranson","tags":["margarita","tequila","sour"],"created":"2024-10-16T00:00:00.000Z","modified":"2024-10-16T00:00:00.000Z","yield":1,"yieldUnit":"drink","ingredients":{"Cocktail":[{"qty":2,"unit":"oz","name":"Reposado Tequila"},{"qty":0.75,"unit":"oz","name":"Lime Juice"},{"qty":0.75,"unit":"oz","name":"Strawberry Rose Syrup"},{"qty":1,"unit":"pinch","name":"salt"}],"Strawberry Rose Syrup":[{"qty":1,"unit":"cup","name":"Water"},{"qty":1,"unit":"cup","name":"Frozen Strawberries"},{"qty":1,"unit":"tbsp","name":"Dried Rose Buds"},{"qty":1,"unit":"cup","name":"Agave Syrup"}],"Garnish":[{"qty":1,"unit":null,"name":"Lime Wheel"}]},"categoryId":"cocktails"}}